annotateiT/GensimBertDataProcessor.py
annotateiT/__init__.py
annotateiT/bertTopic.py
annotateiT/conllProcessing.py
annotateiT/dissertionFunc.py
annotateiT/gensimTopic.py
annotateiT/labelStudio.py
annotateiT/main.py
annotateiT/scrapDissert.py
annotateiT-0.7.3.dist-info/METADATA
annotateiT-0.7.3.dist-info/WHEEL
annotateiT-0.7.3.dist-info/top_level.txt
annotateiT-0.7.3.dist-info/RECORD
