Metadata-Version: 2.1
Name: annotateiT
Version: 0.7.3
Summary: A small example package for annotating text
Home-page: https://github.com/pypa/sampleproject
Author: benjaminK
Author-email: bkeles74@gmail.com
Project-URL: Bug Tracker, https://github.com/pypa/sampleproject/issues
Classifier: Programming Language :: Python :: 3
Classifier: License :: OSI Approved :: MIT License
Classifier: Operating System :: OS Independent
Requires-Python: >=3.9
